allink_core/__init__.py
allink_core/apps/__init__.py
allink_core/apps/config/__init__.py
allink_core/apps/config/abstract_models.py
allink_core/apps/config/admin.py
allink_core/apps/config/cms_menus.py
allink_core/apps/config/cms_toolbars.py
allink_core/apps/config/config.py
allink_core/apps/config/constants.py
allink_core/apps/config/models.py
allink_core/apps/config/utils.py
allink_core/apps/config/migrations/0001_initial.py
allink_core/apps/config/migrations/0002_auto_20190716_0951.py
allink_core/apps/config/migrations/0003_auto_20200124_1010.py
allink_core/apps/config/migrations/0004_allinktitleextension_teaser_link_url.py
allink_core/apps/config/migrations/0005_contact_migration_deletion.py
allink_core/apps/config/migrations/0006_auto_20201103_1630.py
allink_core/apps/config/migrations/__init__.py
allink_core/apps/config/tests/__init__.py
allink_core/apps/config/tests/factories.py
allink_core/apps/config/tests/test_models.py
allink_core/apps/config/tests/test_templatetags.py
allink_core/apps/config/tests/test_utils.py
allink_core/apps/locations/__init__.py
allink_core/apps/locations/abstract_models.py
allink_core/apps/locations/admin.py
allink_core/apps/locations/cms_apps.py
allink_core/apps/locations/cms_menus.py
allink_core/apps/locations/cms_plugins.py
allink_core/apps/locations/cms_toolbars.py
allink_core/apps/locations/config.py
allink_core/apps/locations/managers.py
allink_core/apps/locations/models.py
allink_core/apps/locations/pdf.py
allink_core/apps/locations/sitemaps.py
allink_core/apps/locations/urls.py
allink_core/apps/locations/views.py
allink_core/apps/locations/migrations/0001_initial.py
allink_core/apps/locations/migrations/0002_auto_20190716_0951.py
allink_core/apps/locations/migrations/0003_locations_commercial_register_entry.py
allink_core/apps/locations/migrations/0004_remove_locationsappcontentplugin_filter_fields.py
allink_core/apps/locations/migrations/0005_auto_20191002_2020.py
allink_core-2.8.2.dist-info/LICENSE
allink_core-2.8.2.dist-info/METADATA
allink_core-2.8.2.dist-info/WHEEL
allink_core-2.8.2.dist-info/top_level.txt
allink_core-2.8.2.dist-info/RECORD
